comfy_installer/__init__.py
comfy_installer/cli.py
comfy_installer/constants.py
comfy_installer/inf.py
comfy_installer/installers.py
comfy_installer/utils/__init__.py
comfy_installer/utils/common.py
comfy_installer/utils/file_downloader.py
comfy_installer/utils/gen_status_tracker.py
comfy_installer/utils/logger.py
comfy_installer/utils/node_installer.py
comfy_installer/utils/comfy/__init__.py
comfy_installer/utils/comfy/api.py
comfy_installer/utils/comfy/methods.py
comfy_installer-0.1.17.dist-info/METADATA
comfy_installer-0.1.17.dist-info/WHEEL
comfy_installer-0.1.17.dist-info/entry_points.txt
comfy_installer-0.1.17.dist-info/top_level.txt
comfy_installer-0.1.17.dist-info/RECORD
